<?xml version="1.0" encoding="UTF-8"?>
<!DOCTYPE mapper PUBLIC "-//mybatis.org//DTD Mapper 3.0//EN" "http://mybatis.org/dtd/mybatis-3-mapper.dtd">
<mapper namespace="com.neusoft.bsp.dao.dropshipperMapper">
  <resultMap id="BaseResultMap" type="com.neusoft.bsp.model.dropshipper">
    <!--
      WARNING - @mbg.generated
      This element is automatically generated by MyBatis Generator, do not modify.
    -->
    <constructor>
      <idArg column="DSR_ID" javaType="java.lang.Integer" jdbcType="INTEGER" />
      <arg column="NAME" javaType="java.lang.String" jdbcType="VARCHAR" />
      <arg column="CREATED_BY" javaType="java.lang.String" jdbcType="VARCHAR" />
      <arg column="CREATION_DATE" javaType="java.util.Date" jdbcType="TIMESTAMP" />
      <arg column="LAST_UPDATE_BY" javaType="java.lang.String" jdbcType="VARCHAR" />
      <arg column="LAST_UPDATE_DATE" javaType="java.util.Date" jdbcType="TIMESTAMP" />
      <arg column="CALL_CNT" javaType="java.lang.Integer" jdbcType="INTEGER" />
      <arg column="REMARK" javaType="java.lang.String" jdbcType="VARCHAR" />
      <arg column="STS_CD" javaType="java.lang.String" jdbcType="CHAR" />
      <arg column="REGISTER_DATE" javaType="java.util.Date" jdbcType="TIMESTAMP" />
    </constructor>
  </resultMap>
  <sql id="Base_Column_List">
    <!--
      WARNING - @mbg.generated
      This element is automatically generated by MyBatis Generator, do not modify.
    -->
    DSR_ID, NAME, CREATED_BY, CREATION_DATE, LAST_UPDATE_BY, LAST_UPDATE_DATE, CALL_CNT, 
    REMARK, STS_CD, REGISTER_DATE
  </sql>
  <select id="selectByPrimaryKey" parameterType="java.lang.Integer" resultMap="BaseResultMap">
    <!--
      WARNING - @mbg.generated
      This element is automatically generated by MyBatis Generator, do not modify.
    -->
    select 
    <include refid="Base_Column_List" />
    from dsr_dropshipper
    where DSR_ID = #{dsrId,jdbcType=INTEGER}
  </select>
  <delete id="deleteByPrimaryKey" parameterType="java.lang.Integer">
    <!--
      WARNING - @mbg.generated
      This element is automatically generated by MyBatis Generator, do not modify.
    -->
    delete from dsr_dropshipper
    where DSR_ID = #{dsrId,jdbcType=INTEGER}
  </delete>
  <insert id="insert" parameterType="com.neusoft.bsp.model.dropshipper">
    <!--
      WARNING - @mbg.generated
      This element is automatically generated by MyBatis Generator, do not modify.
    -->
    insert into dsr_dropshipper (DSR_ID, NAME, CREATED_BY, 
      CREATION_DATE, LAST_UPDATE_BY, LAST_UPDATE_DATE, 
      CALL_CNT, REMARK, STS_CD, 
      REGISTER_DATE)
    values (#{dsrId,jdbcType=INTEGER}, #{name,jdbcType=VARCHAR}, #{createdBy,jdbcType=VARCHAR}, 
      #{creationDate,jdbcType=TIMESTAMP}, #{lastUpdateBy,jdbcType=VARCHAR}, #{lastUpdateDate,jdbcType=TIMESTAMP}, 
      #{callCnt,jdbcType=INTEGER}, #{remark,jdbcType=VARCHAR}, #{stsCd,jdbcType=CHAR}, 
      #{registerDate,jdbcType=TIMESTAMP})
  </insert>
  <insert id="insertSelective" parameterType="com.neusoft.bsp.model.dropshipper">
    <!--
      WARNING - @mbg.generated
      This element is automatically generated by MyBatis Generator, do not modify.
    -->
    insert into dsr_dropshipper
    <trim prefix="(" suffix=")" suffixOverrides=",">
      <if test="dsrId != null">
        DSR_ID,
      </if>
      <if test="name != null">
        NAME,
      </if>
      <if test="createdBy != null">
        CREATED_BY,
      </if>
      <if test="creationDate != null">
        CREATION_DATE,
      </if>
      <if test="lastUpdateBy != null">
        LAST_UPDATE_BY,
      </if>
      <if test="lastUpdateDate != null">
        LAST_UPDATE_DATE,
      </if>
      <if test="callCnt != null">
        CALL_CNT,
      </if>
      <if test="remark != null">
        REMARK,
      </if>
      <if test="stsCd != null">
        STS_CD,
      </if>
      <if test="registerDate != null">
        REGISTER_DATE,
      </if>
    </trim>
    <trim prefix="values (" suffix=")" suffixOverrides=",">
      <if test="dsrId != null">
        #{dsrId,jdbcType=INTEGER},
      </if>
      <if test="name != null">
        #{name,jdbcType=VARCHAR},
      </if>
      <if test="createdBy != null">
        #{createdBy,jdbcType=VARCHAR},
      </if>
      <if test="creationDate != null">
        #{creationDate,jdbcType=TIMESTAMP},
      </if>
      <if test="lastUpdateBy != null">
        #{lastUpdateBy,jdbcType=VARCHAR},
      </if>
      <if test="lastUpdateDate != null">
        #{lastUpdateDate,jdbcType=TIMESTAMP},
      </if>
      <if test="callCnt != null">
        #{callCnt,jdbcType=INTEGER},
      </if>
      <if test="remark != null">
        #{remark,jdbcType=VARCHAR},
      </if>
      <if test="stsCd != null">
        #{stsCd,jdbcType=CHAR},
      </if>
      <if test="registerDate != null">
        #{registerDate,jdbcType=TIMESTAMP},
      </if>
    </trim>
  </insert>
  <update id="updateByPrimaryKeySelective" parameterType="com.neusoft.bsp.model.dropshipper">
    <!--
      WARNING - @mbg.generated
      This element is automatically generated by MyBatis Generator, do not modify.
    -->
    update dsr_dropshipper
    <set>
      <if test="name != null">
        NAME = #{name,jdbcType=VARCHAR},
      </if>
      <if test="createdBy != null">
        CREATED_BY = #{createdBy,jdbcType=VARCHAR},
      </if>
      <if test="creationDate != null">
        CREATION_DATE = #{creationDate,jdbcType=TIMESTAMP},
      </if>
      <if test="lastUpdateBy != null">
        LAST_UPDATE_BY = #{lastUpdateBy,jdbcType=VARCHAR},
      </if>
      <if test="lastUpdateDate != null">
        LAST_UPDATE_DATE = #{lastUpdateDate,jdbcType=TIMESTAMP},
      </if>
      <if test="callCnt != null">
        CALL_CNT = #{callCnt,jdbcType=INTEGER},
      </if>
      <if test="remark != null">
        REMARK = #{remark,jdbcType=VARCHAR},
      </if>
      <if test="stsCd != null">
        STS_CD = #{stsCd,jdbcType=CHAR},
      </if>
      <if test="registerDate != null">
        REGISTER_DATE = #{registerDate,jdbcType=TIMESTAMP},
      </if>
    </set>
    where DSR_ID = #{dsrId,jdbcType=INTEGER}
  </update>
  <update id="updateByPrimaryKey" parameterType="com.neusoft.bsp.model.dropshipper">
    <!--
      WARNING - @mbg.generated
      This element is automatically generated by MyBatis Generator, do not modify.
    -->
    update dsr_dropshipper
    set NAME = #{name,jdbcType=VARCHAR},
      CREATED_BY = #{createdBy,jdbcType=VARCHAR},
      CREATION_DATE = #{creationDate,jdbcType=TIMESTAMP},
      LAST_UPDATE_BY = #{lastUpdateBy,jdbcType=VARCHAR},
      LAST_UPDATE_DATE = #{lastUpdateDate,jdbcType=TIMESTAMP},
      CALL_CNT = #{callCnt,jdbcType=INTEGER},
      REMARK = #{remark,jdbcType=VARCHAR},
      STS_CD = #{stsCd,jdbcType=CHAR},
      REGISTER_DATE = #{registerDate,jdbcType=TIMESTAMP}
    where DSR_ID = #{dsrId,jdbcType=INTEGER}
  </update>
</mapper>