<?xml version="1.0" encoding="UTF-8"?>
<!DOCTYPE mapper PUBLIC "-//mybatis.org//DTD Mapper 3.0//EN" "http://mybatis.org/dtd/mybatis-3-mapper.dtd">
<mapper namespace="com.neusoft.bsp.dao.parameterMapper">
  <resultMap id="BaseResultMap" type="com.neusoft.bsp.model.parameter">
    <!--
      WARNING - @mbg.generated
      This element is automatically generated by MyBatis Generator, do not modify.
    -->
    <constructor>
      <idArg column="PAR_ID" javaType="java.lang.Integer" jdbcType="INTEGER" />
      <arg column="PARAM_CD" javaType="java.lang.String" jdbcType="VARCHAR" />
      <arg column="PARAM_VALUE" javaType="java.lang.String" jdbcType="VARCHAR" />
      <arg column="CREATED_BY" javaType="java.lang.String" jdbcType="VARCHAR" />
      <arg column="CREATION_DATE" javaType="java.util.Date" jdbcType="TIMESTAMP" />
      <arg column="LAST_UPDATE_BY" javaType="java.lang.String" jdbcType="VARCHAR" />
      <arg column="LAST_UPDATE_DATE" javaType="java.util.Date" jdbcType="TIMESTAMP" />
      <arg column="CALL_CNT" javaType="java.lang.Integer" jdbcType="INTEGER" />
      <arg column="REMARK" javaType="java.lang.String" jdbcType="VARCHAR" />
      <arg column="STS_CD" javaType="java.lang.String" jdbcType="CHAR" />
    </constructor>
  </resultMap>
  <resultMap id="ResultMapWithBLOBs" type="com.neusoft.bsp.model.parameter">
    <!--
      WARNING - @mbg.generated
      This element is automatically generated by MyBatis Generator, do not modify.
    -->
    <constructor>
      <idArg column="PAR_ID" javaType="java.lang.Integer" jdbcType="INTEGER" />
      <arg column="PARAM_CD" javaType="java.lang.String" jdbcType="VARCHAR" />
      <arg column="PARAM_VALUE" javaType="java.lang.String" jdbcType="VARCHAR" />
      <arg column="CREATED_BY" javaType="java.lang.String" jdbcType="VARCHAR" />
      <arg column="CREATION_DATE" javaType="java.util.Date" jdbcType="TIMESTAMP" />
      <arg column="LAST_UPDATE_BY" javaType="java.lang.String" jdbcType="VARCHAR" />
      <arg column="LAST_UPDATE_DATE" javaType="java.util.Date" jdbcType="TIMESTAMP" />
      <arg column="CALL_CNT" javaType="java.lang.Integer" jdbcType="INTEGER" />
      <arg column="REMARK" javaType="java.lang.String" jdbcType="VARCHAR" />
      <arg column="STS_CD" javaType="java.lang.String" jdbcType="CHAR" />
      <arg column="DESCRIPTION" javaType="java.lang.String" jdbcType="LONGVARCHAR" />
    </constructor>
  </resultMap>
  <sql id="Base_Column_List">
    <!--
      WARNING - @mbg.generated
      This element is automatically generated by MyBatis Generator, do not modify.
    -->
    PAR_ID, PARAM_CD, PARAM_VALUE, CREATED_BY, CREATION_DATE, LAST_UPDATE_BY, LAST_UPDATE_DATE, 
    CALL_CNT, REMARK, STS_CD
  </sql>
  <sql id="Blob_Column_List">
    <!--
      WARNING - @mbg.generated
      This element is automatically generated by MyBatis Generator, do not modify.
    -->
    DESCRIPTION
  </sql>
  <select id="selectByPrimaryKey" parameterType="java.lang.Integer" resultMap="ResultMapWithBLOBs">
    <!--
      WARNING - @mbg.generated
      This element is automatically generated by MyBatis Generator, do not modify.
    -->
    select 
    <include refid="Base_Column_List" />
    ,
    <include refid="Blob_Column_List" />
    from par_parameter
    where PAR_ID = #{parId,jdbcType=INTEGER}
  </select>
  <delete id="deleteByPrimaryKey" parameterType="java.lang.Integer">
    <!--
      WARNING - @mbg.generated
      This element is automatically generated by MyBatis Generator, do not modify.
    -->
    delete from par_parameter
    where PAR_ID = #{parId,jdbcType=INTEGER}
  </delete>
  <insert id="insert" parameterType="com.neusoft.bsp.model.parameter">
    <!--
      WARNING - @mbg.generated
      This element is automatically generated by MyBatis Generator, do not modify.
    -->
    insert into par_parameter (PAR_ID, PARAM_CD, PARAM_VALUE, 
      CREATED_BY, CREATION_DATE, LAST_UPDATE_BY, 
      LAST_UPDATE_DATE, CALL_CNT, REMARK, 
      STS_CD, DESCRIPTION)
    values (#{parId,jdbcType=INTEGER}, #{paramCd,jdbcType=VARCHAR}, #{paramValue,jdbcType=VARCHAR}, 
      #{createdBy,jdbcType=VARCHAR}, #{creationDate,jdbcType=TIMESTAMP}, #{lastUpdateBy,jdbcType=VARCHAR}, 
      #{lastUpdateDate,jdbcType=TIMESTAMP}, #{callCnt,jdbcType=INTEGER}, #{remark,jdbcType=VARCHAR}, 
      #{stsCd,jdbcType=CHAR}, #{description,jdbcType=LONGVARCHAR})
  </insert>
  <insert id="insertSelective" parameterType="com.neusoft.bsp.model.parameter">
    <!--
      WARNING - @mbg.generated
      This element is automatically generated by MyBatis Generator, do not modify.
    -->
    insert into par_parameter
    <trim prefix="(" suffix=")" suffixOverrides=",">
      <if test="parId != null">
        PAR_ID,
      </if>
      <if test="paramCd != null">
        PARAM_CD,
      </if>
      <if test="paramValue != null">
        PARAM_VALUE,
      </if>
      <if test="createdBy != null">
        CREATED_BY,
      </if>
      <if test="creationDate != null">
        CREATION_DATE,
      </if>
      <if test="lastUpdateBy != null">
        LAST_UPDATE_BY,
      </if>
      <if test="lastUpdateDate != null">
        LAST_UPDATE_DATE,
      </if>
      <if test="callCnt != null">
        CALL_CNT,
      </if>
      <if test="remark != null">
        REMARK,
      </if>
      <if test="stsCd != null">
        STS_CD,
      </if>
      <if test="description != null">
        DESCRIPTION,
      </if>
    </trim>
    <trim prefix="values (" suffix=")" suffixOverrides=",">
      <if test="parId != null">
        #{parId,jdbcType=INTEGER},
      </if>
      <if test="paramCd != null">
        #{paramCd,jdbcType=VARCHAR},
      </if>
      <if test="paramValue != null">
        #{paramValue,jdbcType=VARCHAR},
      </if>
      <if test="createdBy != null">
        #{createdBy,jdbcType=VARCHAR},
      </if>
      <if test="creationDate != null">
        #{creationDate,jdbcType=TIMESTAMP},
      </if>
      <if test="lastUpdateBy != null">
        #{lastUpdateBy,jdbcType=VARCHAR},
      </if>
      <if test="lastUpdateDate != null">
        #{lastUpdateDate,jdbcType=TIMESTAMP},
      </if>
      <if test="callCnt != null">
        #{callCnt,jdbcType=INTEGER},
      </if>
      <if test="remark != null">
        #{remark,jdbcType=VARCHAR},
      </if>
      <if test="stsCd != null">
        #{stsCd,jdbcType=CHAR},
      </if>
      <if test="description != null">
        #{description,jdbcType=LONGVARCHAR},
      </if>
    </trim>
  </insert>
  <update id="updateByPrimaryKeySelective" parameterType="com.neusoft.bsp.model.parameter">
    <!--
      WARNING - @mbg.generated
      This element is automatically generated by MyBatis Generator, do not modify.
    -->
    update par_parameter
    <set>
      <if test="paramCd != null">
        PARAM_CD = #{paramCd,jdbcType=VARCHAR},
      </if>
      <if test="paramValue != null">
        PARAM_VALUE = #{paramValue,jdbcType=VARCHAR},
      </if>
      <if test="createdBy != null">
        CREATED_BY = #{createdBy,jdbcType=VARCHAR},
      </if>
      <if test="creationDate != null">
        CREATION_DATE = #{creationDate,jdbcType=TIMESTAMP},
      </if>
      <if test="lastUpdateBy != null">
        LAST_UPDATE_BY = #{lastUpdateBy,jdbcType=VARCHAR},
      </if>
      <if test="lastUpdateDate != null">
        LAST_UPDATE_DATE = #{lastUpdateDate,jdbcType=TIMESTAMP},
      </if>
      <if test="callCnt != null">
        CALL_CNT = #{callCnt,jdbcType=INTEGER},
      </if>
      <if test="remark != null">
        REMARK = #{remark,jdbcType=VARCHAR},
      </if>
      <if test="stsCd != null">
        STS_CD = #{stsCd,jdbcType=CHAR},
      </if>
      <if test="description != null">
        DESCRIPTION = #{description,jdbcType=LONGVARCHAR},
      </if>
    </set>
    where PAR_ID = #{parId,jdbcType=INTEGER}
  </update>
  <update id="updateByPrimaryKeyWithBLOBs" parameterType="com.neusoft.bsp.model.parameter">
    <!--
      WARNING - @mbg.generated
      This element is automatically generated by MyBatis Generator, do not modify.
    -->
    update par_parameter
    set PARAM_CD = #{paramCd,jdbcType=VARCHAR},
      PARAM_VALUE = #{paramValue,jdbcType=VARCHAR},
      CREATED_BY = #{createdBy,jdbcType=VARCHAR},
      CREATION_DATE = #{creationDate,jdbcType=TIMESTAMP},
      LAST_UPDATE_BY = #{lastUpdateBy,jdbcType=VARCHAR},
      LAST_UPDATE_DATE = #{lastUpdateDate,jdbcType=TIMESTAMP},
      CALL_CNT = #{callCnt,jdbcType=INTEGER},
      REMARK = #{remark,jdbcType=VARCHAR},
      STS_CD = #{stsCd,jdbcType=CHAR},
      DESCRIPTION = #{description,jdbcType=LONGVARCHAR}
    where PAR_ID = #{parId,jdbcType=INTEGER}
  </update>
  <update id="updateByPrimaryKey" parameterType="com.neusoft.bsp.model.parameter">
    <!--
      WARNING - @mbg.generated
      This element is automatically generated by MyBatis Generator, do not modify.
    -->
    update par_parameter
    set PARAM_CD = #{paramCd,jdbcType=VARCHAR},
      PARAM_VALUE = #{paramValue,jdbcType=VARCHAR},
      CREATED_BY = #{createdBy,jdbcType=VARCHAR},
      CREATION_DATE = #{creationDate,jdbcType=TIMESTAMP},
      LAST_UPDATE_BY = #{lastUpdateBy,jdbcType=VARCHAR},
      LAST_UPDATE_DATE = #{lastUpdateDate,jdbcType=TIMESTAMP},
      CALL_CNT = #{callCnt,jdbcType=INTEGER},
      REMARK = #{remark,jdbcType=VARCHAR},
      STS_CD = #{stsCd,jdbcType=CHAR}
    where PAR_ID = #{parId,jdbcType=INTEGER}
  </update>
</mapper>